gtfsblocks/__init__.py
gtfsblocks/gtfs.py
gtfsblocks/tests/test_gtfs.py
gtfsblocks-0.1.2.dist-info/METADATA
gtfsblocks-0.1.2.dist-info/WHEEL
gtfsblocks-0.1.2.dist-info/licenses/LICENSE
gtfsblocks-0.1.2.dist-info/RECORD
