Metadata-Version: 2.4
Name: gtfsblocks
Version: 0.1.2
Summary: Python package for processing GTFS feeds to assemble bus blocks and relevant data 
Project-URL: Homepage, https://github.com/dan-mccabe/gtfsblocks
Project-URL: Issues, https://github.com/dan-mccabe/gtfsblocks/issues
Author-email: Dan McCabe <Dan.McCabe@nrel.gov>
License: BSD 3-Clause
License-File: LICENSE
Classifier: Development Status :: 3 - Alpha
Classifier: Operating System :: OS Independent
Classifier: Programming Language :: Python :: 3
Requires-Python: >=3.7
Requires-Dist: numpy>=1.26
Requires-Dist: pandas>=2.2
Requires-Dist: plotly>=5.24
Provides-Extra: dev
Requires-Dist: ipykernel; extra == 'dev'
Requires-Dist: nbformat; extra == 'dev'
Requires-Dist: pre-commit; extra == 'dev'
Requires-Dist: ruff; extra == 'dev'
